flaschenclient/__init__.py
flaschenclient/flaschenclient.py
flaschenclient/imagewrapper.py
flaschenclient/limits.py
flaschenclient/motion.py
flaschenclient/sequence.py
flaschenclient-0.1.4.dist-info/LICENSE
flaschenclient-0.1.4.dist-info/METADATA
flaschenclient-0.1.4.dist-info/WHEEL
flaschenclient-0.1.4.dist-info/top_level.txt
flaschenclient-0.1.4.dist-info/RECORD
