Metadata-Version: 2.1
Name: flaschenclient
Version: 0.1.4
Summary: With this python library you can send simple animations to the flaschen taschen server (fork).
Home-page: https://github.com/werling/flaschenclient
Author: Sebastian Werling
Author-email: sebastian.werling@gmail.com
License: UNKNOWN
Platform: UNKNOWN
Classifier: Programming Language :: Python :: 3
Classifier: License :: OSI Approved :: GNU Lesser General Public License v2 or later (LGPLv2+)
Classifier: Operating System :: OS Independent
